MANIFEST.in
README.rst
setup.py
collective/__init__.py
collective.microdata.event.egg-info/PKG-INFO
collective.microdata.event.egg-info/SOURCES.txt
collective.microdata.event.egg-info/dependency_links.txt
collective.microdata.event.egg-info/entry_points.txt
collective.microdata.event.egg-info/namespace_packages.txt
collective.microdata.event.egg-info/not-zip-safe
collective.microdata.event.egg-info/requires.txt
collective.microdata.event.egg-info/top_level.txt
collective/microdata/__init__.py
collective/microdata/event/__init__.py
collective/microdata/event/adapter.py
collective/microdata/event/configure.zcml
collective/microdata/event/indexer.py
collective/microdata/event/interfaces.py
collective/microdata/event/browser/__init__.py
collective/microdata/event/browser/configure.zcml
collective/microdata/event/browser/view.py
collective/microdata/event/browser/templates/event_view.pt
collective/microdata/event/browser/templates/folder_listing_item.pt
collective/microdata/event/browser/templates/folder_summary_view_item.pt
collective/microdata/event/locales/collective.microdata.event.pot
collective/microdata/event/locales/rebuildPo.sh
collective/microdata/event/locales/it/LC_MESSAGES/collective.microdata.event.po
collective/microdata/event/profiles/default/browserlayer.xml
collective/microdata/event/profiles/default/metadata.xml
docs/HISTORY.txt
docs/INSTALL.txt
docs/LICENSE.GPL
docs/LICENSE.txt