Metadata-Version: 1.1
Name: collective.microdata.event
Version: 0.2
Summary: Add microdata (scheda.org) support to Plone events
Home-page: http://plone.org/products/collective.microdata.event
Author: keul
Author-email: luca@keul.it
License: GPL
Keywords: plone microdata schema.org html5 event
Platform: UNKNOWN
Classifier: Development Status :: 4 - Beta
Classifier: Framework :: Plone
Classifier: Framework :: Plone :: 4.2
Classifier: Programming Language :: Python
